setup.py
gb_pdistributions/Binomialdistribution.py
gb_pdistributions/Gaussiandistribution.py
gb_pdistributions/Generaldistribution.py
gb_pdistributions/__init__.py
gb_pdistributions.egg-info/PKG-INFO
gb_pdistributions.egg-info/SOURCES.txt
gb_pdistributions.egg-info/dependency_links.txt
gb_pdistributions.egg-info/not-zip-safe
gb_pdistributions.egg-info/top_level.txt